latlonconv/__init__.py
latlonconv/latlon_conv.py
latlonconv-1.0.1.dist-info/LICENSE
latlonconv-1.0.1.dist-info/METADATA
latlonconv-1.0.1.dist-info/WHEEL
latlonconv-1.0.1.dist-info/top_level.txt
latlonconv-1.0.1.dist-info/RECORD
