Metadata-Version: 2.1
Name: latlonconv
Version: 1.0.1
Summary: Methods for representing geographic coordinates
Home-page: UNKNOWN
Author: Michael Gruber
Author-email: michael1_gruber@protonmail.com
License: UNKNOWN
Platform: UNKNOWN
Classifier: Development Status :: 7 - Inactive
Classifier: Intended Audience :: Other Audience
Classifier: License :: OSI Approved :: GNU General Public License v3 (GPLv3)
Classifier: Operating System :: OS Independent
Classifier: Programming Language :: Python :: 3
Requires-Python: >=3.6
